symbtools/__init__.py
symbtools/auxiliary.py
symbtools/core.py
symbtools/interactive_aux.py
symbtools/meshtools.py
symbtools/modeltools.py
symbtools/mpctools.py
symbtools/noncommutativetools.py
symbtools/pickle_tools.py
symbtools/release.py
symbtools/time_deriv.py
symbtools/unittesthelper.py
symbtools/visualisation.py
symbtools-0.4.1.dist-info/licenses/LICENSE
symbtools-0.4.1.dist-info/METADATA
symbtools-0.4.1.dist-info/WHEEL
symbtools-0.4.1.dist-info/top_level.txt
symbtools-0.4.1.dist-info/RECORD
