Metadata-Version: 2.4
Name: symbtools
Version: 0.4.1
Summary: Symbolic calculations related to dynamical systems.
Author-email: Carsten Knoll <firstname.lastname@tu-dresden.de>, Klemens Fritzsche <firstname2.lastname@tu-dresden.de>
License: Copyright (c) 2013-2016 Carsten Knoll, Klemens Fritzsche
Project-URL: Homepage, https://github.com/TUD-RST/symbtools
Classifier: Development Status :: 4 - Beta
Classifier: Intended Audience :: Developers
Classifier: Programming Language :: Python :: 3
Requires-Python: >=3.10
License-File: LICENSE
Requires-Dist: sympy!=1.11.*,>=1.7
Requires-Dist: numpy>=1.10.4
Requires-Dist: scipy>=1.0
Requires-Dist: ipydex>=0.8.2
Requires-Dist: pytest
Requires-Dist: matplotlib
Provides-Extra: mpc
Requires-Dist: casadi; extra == "mpc"
Provides-Extra: visualization
Requires-Dist: matplotlib>=3.1; extra == "visualization"
Requires-Dist: ipywidgets>=7.5; extra == "visualization"
Dynamic: license-file
